{
  "swagger": "2.0",
  "info": {
    "version": "1.0.0",
    "title": "typescript test",
    "description": "Documentation automatically generated by the <b>swagger-autogen</b> module."
  },
  "host": "localhost:5000",
  "basePath": "/",
  "tags": [
    {
      "name": "User",
      "description": "Endpoints"
    }
  ],
  "schemes": [
    "http"
  ],
  "securityDefinitions": {
    "apiKeyAuth": {
      "type": "apiKey",
      "in": "header",
      "name": "X-API-KEY",
      "description": "any description..."
    }
  },
  "consumes": [
    "application/json"
  ],
  "produces": [
    "application/json"
  ],
  "paths": {
    "/api/book/": {
      "post": {
        "tags": [],
        "description": "",
        "parameters": [
          {
            "name": "obj",
            "in": "body",
            "schema": {
              "type": "object",
              "properties": {
                "title": {
                  "example": "any"
                },
                "author": {
                  "example": "any"
                },
                "price": {
                  "example": "any"
                }
              }
            }
          }
        ],
        "responses": {}
      },
      "get": {
        "tags": [],
        "description": "",
        "parameters": [],
        "responses": {}
      }
    },
    "/api/book/{bookId}": {
      "get": {
        "tags": [],
        "description": "",
        "parameters": [
          {
            "name": "bookId",
            "in": "path",
            "required": true,
            "type": "string"
          }
        ],
        "responses": {}
      },
      "put": {
        "tags": [],
        "description": "",
        "parameters": [
          {
            "name": "bookId",
            "in": "path",
            "required": true,
            "type": "string"
          },
          {
            "name": "obj",
            "in": "body",
            "schema": {
              "type": "object",
              "properties": {
                "title": {
                  "example": "any"
                },
                "author": {
                  "example": "any"
                },
                "price": {
                  "example": "any"
                }
              }
            }
          }
        ],
        "responses": {}
      },
      "delete": {
        "tags": [],
        "description": "",
        "parameters": [
          {
            "name": "bookId",
            "in": "path",
            "required": true,
            "type": "string"
          }
        ],
        "responses": {}
      }
    }
  },
  "definitions": {},
  "schemas": [
    "http",
    "https"
  ]
}